vecml/__init__.py
vecml/client.py
vecml/vdb_pb2.py
vecml/vdb_pb2_grpc.py
vecml-0.1.2.dist-info/LICENSE
vecml-0.1.2.dist-info/METADATA
vecml-0.1.2.dist-info/WHEEL
vecml-0.1.2.dist-info/top_level.txt
vecml-0.1.2.dist-info/RECORD
