Metadata-Version: 2.1
Name: vecml
Version: 0.1.2
Summary: The VecML client
Home-page: https://www.vecml.com
Author: VecML Inc
Author-email: support@vecml.com
License: Apache-2.0
License-File: LICENSE
Requires-Dist: grpcio
Requires-Dist: numpy
Requires-Dist: scipy
Requires-Dist: tqdm
Requires-Dist: protobuf
Requires-Dist: requests
